phywhisperer/__init__.py
phywhisperer/protocol.py
phywhisperer/sniffer.py
phywhisperer/usb.py
phywhisperer/firmware/__init__.py
phywhisperer/firmware/defines.v
phywhisperer/firmware/generate_firmware_files.py
phywhisperer/firmware/phywhisperer.py
phywhisperer/interface/__init__.py
phywhisperer/interface/bootloader_sam3u.py
phywhisperer/interface/naeusb.py
phywhisperer/interface/program_fpga.py
phywhisperer/interface/serial.py
phywhisperer-0.1.0.dist-info/METADATA
phywhisperer-0.1.0.dist-info/WHEEL
phywhisperer-0.1.0.dist-info/top_level.txt
phywhisperer-0.1.0.dist-info/RECORD
