Metadata-Version: 2.1
Name: phywhisperer
Version: 0.1.0
Summary: PhyWhisperer USB Hardware Trigger
Home-page: http://www.PhyWhisperer.com
Author: NewAE Technology Inc.
Author-email: coflynn@newae.com
License: GPLv3
Project-URL: Documentation, https://phywhispererusb.readthedocs.io
Project-URL: Source, https://github.com/newaetech/phywhispererusb
Project-URL: Issue Tracker, https://github.com/newaetech/phywhispererusb/issues
Platform: UNKNOWN
Requires-Python: >3.4
Requires-Dist: pyserial
Requires-Dist: crcmod
Requires-Dist: pyusb
